TestRailAPIClient.py
TestRailListener.py
TestRailPreRunModifier.py
u_robotframework_testrail-1.4.dist-info/LICENSE
u_robotframework_testrail-1.4.dist-info/METADATA
u_robotframework_testrail-1.4.dist-info/WHEEL
u_robotframework_testrail-1.4.dist-info/top_level.txt
u_robotframework_testrail-1.4.dist-info/RECORD
