Metadata-Version: 2.1
Name: u-robotframework-testrail
Version: 1.4
Summary: Updated fork of Robot Framework library, listener and pre-run modifier for working with TestRail
Home-page: https://github.com/hwceong-edu/u-robotframework-testrail/
Author: Original auther: JSC PETER-SERVICE
Author-email: hceong@sfu.ca
License: Apache License 2.0
Keywords: testing testautomation robotframework testrail
Platform: UNKNOWN
Classifier: Development Status :: 5 - Production/Stable
Classifier: Intended Audience :: Developers
Classifier: Topic :: Software Development :: Testing
Classifier: License :: OSI Approved :: Apache Software License
Classifier: Programming Language :: Python :: 3.5
Classifier: Programming Language :: Python :: 3.6
Classifier: Framework :: Robot Framework :: Library
License-File: LICENSE
Requires-Dist: requests (>=2.20.0)
Requires-Dist: robotframework (>=3.0.3)
Requires-Dist: future (==0.16.0) ; python_version <= "2.7"
